Workbook

Sheet Dashboard
B1: DigiShop AI — Project Dashboard
B2: Phase 1: Web App Launch · 0 → 1,000 Vendors · Live status from Task Tracker
B4: STATUS SUMMARY
B5: To Do | C5: In Progress | D5: In Review | E5: Done | F5: Blocked
B6: =COUNTIF('Task Tracker'!$L$3:$L$137,"To Do") -> 31 | C6: =COUNTIF('Task Tracker'!$L$3:$L$137,"In Progress") -> 52 | D6: =COUNTIF('Task Tracker'!$L$3:$L$137,"In Review") -> 52 | E6: =COUNTIF('Task Tracker'!$L$3:$L$137,"Done") -> 0 | F6: =COUNTIF('Task Tracker'!$L$3:$L$137,"Blocked") -> 0
B8: TOTALS | E8: DISTRIBUTION (Per Member)
B9: Vendor tasks (V1–V4) | C9: =COUNTIF('Task Tracker'!$C$3:$C$137,"Vendor") -> 75 | E9: V1 | F9: =COUNTIF('Task Tracker'!$B$3:$B$137,"V1") -> 16
B10: Admin tasks (A1–A4) | C10: =COUNTIF('Task Tracker'!$C$3:$C$137,"Admin") -> 60 | E10: V2 | F10: =COUNTIF('Task Tracker'!$B$3:$B$137,"V2") -> 19
B11: Grand total | C11: =COUNTA('Task Tracker'!$B$3:$B$137) -> 135 | E11: V3 | F11: =COUNTIF('Task Tracker'!$B$3:$B$137,"V3") -> 17
E12: V4 | F12: =COUNTIF('Task Tracker'!$B$3:$B$137,"V4") -> 23
E13: A1 | F13: =COUNTIF('Task Tracker'!$B$3:$B$137,"A1") -> 15
E14: A2 | F14: =COUNTIF('Task Tracker'!$B$3:$B$137,"A2") -> 14
E15: A3 | F15: =COUNTIF('Task Tracker'!$B$3:$B$137,"A3") -> 14
E16: A4 | F16: =COUNTIF('Task Tracker'!$B$3:$B$137,"A4") -> 17
B18: STATUS BREAKDOWN BY MEMBER
B19: Member | C19: To Do | D19: In Progress | E19: In Review | F19: Done | G19: Blocked | H19: Total
B20: V1 | C20: =COUNTIFS('Task Tracker'!$B$3:$B$137,"V1",'Task Tracker'!$L$3:$L$137,"To Do") -> 0 | D20: =COUNTIFS('Task Tracker'!$B$3:$B$137,"V1",'Task Tracker'!$L$3:$L$137,"In Progress") -> 16 | E20: =COUNTIFS('Task Tracker'!$B$3:$B$137,"V1",'Task Tracker'!$L$3:$L$137,"In Review") -> 0 | F20: =COUNTIFS('Task Tracker'!$B$3:$B$137,"V1",'Task Tracker'!$L$3:$L$137,"Done") -> 0 | G20: =COUNTIFS('Task Tracker'!$B$3:$B$137,"V1",'Task Tracker'!$L$3:$L$137,"Blocked") -> 0 | H20: =COUNTIF('Task Tracker'!$B$3:$B$137,"V1") -> 16
B21: V2 | C21: =COUNTIFS('Task Tracker'!$B$3:$B$137,"V2",'Task Tracker'!$L$3:$L$137,"To Do") -> 0 | D21: =COUNTIFS('Task Tracker'!$B$3:$B$137,"V2",'Task Tracker'!$L$3:$L$137,"In Progress") -> 19 | E21: =COUNTIFS('Task Tracker'!$B$3:$B$137,"V2",'Task Tracker'!$L$3:$L$137,"In Review") -> 0 | F21: =COUNTIFS('Task Tracker'!$B$3:$B$137,"V2",'Task Tracker'!$L$3:$L$137,"Done") -> 0 | G21: =COUNTIFS('Task Tracker'!$B$3:$B$137,"V2",'Task Tracker'!$L$3:$L$137,"Blocked") -> 0 | H21: =COUNTIF('Task Tracker'!$B$3:$B$137,"V2") -> 19
B22: V3 | C22: =COUNTIFS('Task Tracker'!$B$3:$B$137,"V3",'Task Tracker'!$L$3:$L$137,"To Do") -> 0 | D22: =COUNTIFS('Task Tracker'!$B$3:$B$137,"V3",'Task Tracker'!$L$3:$L$137,"In Progress") -> 17 | E22: =COUNTIFS('Task Tracker'!$B$3:$B$137,"V3",'Task Tracker'!$L$3:$L$137,"In Review") -> 0 | F22: =COUNTIFS('Task Tracker'!$B$3:$B$137,"V3",'Task Tracker'!$L$3:$L$137,"Done") -> 0 | G22: =COUNTIFS('Task Tracker'!$B$3:$B$137,"V3",'Task Tracker'!$L$3:$L$137,"Blocked") -> 0 | H22: =COUNTIF('Task Tracker'!$B$3:$B$137,"V3") -> 17
B23: V4 | C23: =COUNTIFS('Task Tracker'!$B$3:$B$137,"V4",'Task Tracker'!$L$3:$L$137,"To Do") -> 23 | D23: =COUNTIFS('Task Tracker'!$B$3:$B$137,"V4",'Task Tracker'!$L$3:$L$137,"In Progress") -> 0 | E23: =COUNTIFS('Task Tracker'!$B$3:$B$137,"V4",'Task Tracker'!$L$3:$L$137,"In Review") -> 0 | F23: =COUNTIFS('Task Tracker'!$B$3:$B$137,"V4",'Task Tracker'!$L$3:$L$137,"Done") -> 0 | G23: =COUNTIFS('Task Tracker'!$B$3:$B$137,"V4",'Task Tracker'!$L$3:$L$137,"Blocked") -> 0 | H23: =COUNTIF('Task Tracker'!$B$3:$B$137,"V4") -> 23
B24: A1 | C24: =COUNTIFS('Task Tracker'!$B$3:$B$137,"A1",'Task Tracker'!$L$3:$L$137,"To Do") -> 0 | D24: =COUNTIFS('Task Tracker'!$B$3:$B$137,"A1",'Task Tracker'!$L$3:$L$137,"In Progress") -> 0 | E24: =COUNTIFS('Task Tracker'!$B$3:$B$137,"A1",'Task Tracker'!$L$3:$L$137,"In Review") -> 15 | F24: =COUNTIFS('Task Tracker'!$B$3:$B$137,"A1",'Task Tracker'!$L$3:$L$137,"Done") -> 0 | G24: =COUNTIFS('Task Tracker'!$B$3:$B$137,"A1",'Task Tracker'!$L$3:$L$137,"Blocked") -> 0 | H24: =COUNTIF('Task Tracker'!$B$3:$B$137,"A1") -> 15
B25: A2 | C25: =COUNTIFS('Task Tracker'!$B$3:$B$137,"A2",'Task Tracker'!$L$3:$L$137,"To Do") -> 1 | D25: =COUNTIFS('Task Tracker'!$B$3:$B$137,"A2",'Task Tracker'!$L$3:$L$137,"In Progress") -> 0 | E25: =COUNTIFS('Task Tracker'!$B$3:$B$137,"A2",'Task Tracker'!$L$3:$L$137,"In Review") -> 13 | F25: =COUNTIFS('Task Tracker'!$B$3:$B$137,"A2",'Task Tracker'!$L$3:$L$137,"Done") -> 0 | G25: =COUNTIFS('Task Tracker'!$B$3:$B$137,"A2",'Task Tracker'!$L$3:$L$137,"Blocked") -> 0 | H25: =COUNTIF('Task Tracker'!$B$3:$B$137,"A2") -> 14
B26: A3 | C26: =COUNTIFS('Task Tracker'!$B$3:$B$137,"A3",'Task Tracker'!$L$3:$L$137,"To Do") -> 0 | D26: =COUNTIFS('Task Tracker'!$B$3:$B$137,"A3",'Task Tracker'!$L$3:$L$137,"In Progress") -> 0 | E26: =COUNTIFS('Task Tracker'!$B$3:$B$137,"A3",'Task Tracker'!$L$3:$L$137,"In Review") -> 14 | F26: =COUNTIFS('Task Tracker'!$B$3:$B$137,"A3",'Task Tracker'!$L$3:$L$137,"Done") -> 0 | G26: =COUNTIFS('Task Tracker'!$B$3:$B$137,"A3",'Task Tracker'!$L$3:$L$137,"Blocked") -> 0 | H26: =COUNTIF('Task Tracker'!$B$3:$B$137,"A3") -> 14
B27: A4 | C27: =COUNTIFS('Task Tracker'!$B$3:$B$137,"A4",'Task Tracker'!$L$3:$L$137,"To Do") -> 7 | D27: =COUNTIFS('Task Tracker'!$B$3:$B$137,"A4",'Task Tracker'!$L$3:$L$137,"In Progress") -> 0 | E27: =COUNTIFS('Task Tracker'!$B$3:$B$137,"A4",'Task Tracker'!$L$3:$L$137,"In Review") -> 10 | F27: =COUNTIFS('Task Tracker'!$B$3:$B$137,"A4",'Task Tracker'!$L$3:$L$137,"Done") -> 0 | G27: =COUNTIFS('Task Tracker'!$B$3:$B$137,"A4",'Task Tracker'!$L$3:$L$137,"Blocked") -> 0 | H27: =COUNTIF('Task Tracker'!$B$3:$B$137,"A4") -> 17
B28: TOTAL | C28: =COUNTIF('Task Tracker'!$L$3:$L$137,"To Do") -> 31 | D28: =COUNTIF('Task Tracker'!$L$3:$L$137,"In Progress") -> 52 | E28: =COUNTIF('Task Tracker'!$L$3:$L$137,"In Review") -> 52 | F28: =COUNTIF('Task Tracker'!$L$3:$L$137,"Done") -> 0 | G28: =COUNTIF('Task Tracker'!$L$3:$L$137,"Blocked") -> 0 | H28: =COUNTA('Task Tracker'!$B$3:$B$137) -> 135
B30: STATUS BREAKDOWN BY SIDE
B31: Side | C31: To Do | D31: In Progress | E31: In Review | F31: Done | G31: Blocked | H31: Total
B32: Vendor | C32: =COUNTIFS('Task Tracker'!$C$3:$C$137,"Vendor",'Task Tracker'!$L$3:$L$137,"To Do") -> 23 | D32: =COUNTIFS('Task Tracker'!$C$3:$C$137,"Vendor",'Task Tracker'!$L$3:$L$137,"In Progress") -> 52 | E32: =COUNTIFS('Task Tracker'!$C$3:$C$137,"Vendor",'Task Tracker'!$L$3:$L$137,"In Review") -> 0 | F32: =COUNTIFS('Task Tracker'!$C$3:$C$137,"Vendor",'Task Tracker'!$L$3:$L$137,"Done") -> 0 | G32: =COUNTIFS('Task Tracker'!$C$3:$C$137,"Vendor",'Task Tracker'!$L$3:$L$137,"Blocked") -> 0 | H32: =COUNTIF('Task Tracker'!$C$3:$C$137,"Vendor") -> 75
B33: Admin | C33: =COUNTIFS('Task Tracker'!$C$3:$C$137,"Admin",'Task Tracker'!$L$3:$L$137,"To Do") -> 8 | D33: =COUNTIFS('Task Tracker'!$C$3:$C$137,"Admin",'Task Tracker'!$L$3:$L$137,"In Progress") -> 0 | E33: =COUNTIFS('Task Tracker'!$C$3:$C$137,"Admin",'Task Tracker'!$L$3:$L$137,"In Review") -> 52 | F33: =COUNTIFS('Task Tracker'!$C$3:$C$137,"Admin",'Task Tracker'!$L$3:$L$137,"Done") -> 0 | G33: =COUNTIFS('Task Tracker'!$C$3:$C$137,"Admin",'Task Tracker'!$L$3:$L$137,"Blocked") -> 0 | H33: =COUNTIF('Task Tracker'!$C$3:$C$137,"Admin") -> 60
B35: PRIORITY BREAKDOWN
B36: Priority | C36: Count
B37: P0 | C37: =COUNTIF('Task Tracker'!$I$3:$I$137,"P0") -> 99
B38: P1 | C38: =COUNTIF('Task Tracker'!$I$3:$I$137,"P1") -> 36
B40: STATUS DEFINITIONS
B41: To Do | C41: Not yet started.
B42: In Progress | C42: Actively being worked on.
B43: In Review | C43: PR open, awaiting review.
B44: Done | C44: Merged to main.
B45: Blocked | C45: Cannot proceed — flag lead within 4 hours.

Sheet Team Roster
A1: DigiShop AI — Team Roster (8 Members, 2 Sides)
A2: Member | B2: Name (fill in) | C2: Role — Vertical Slice (Full-Stack, UI + Backend) | D2: Repository | E2: Git Branch | F2: Side
A3: V1 | B3: Hafsa Shaban | C3: Vendor Auth, Onboarding, Profile & Subscription (UI + Backend) | D3: digishop-vendor | E3: feature/v1-auth-onboarding | F3: Vendor
A4: V2 | B4: Amna Shaban | C4: Vendor Dashboard, Live Analytics & Storefront Theme Engine (UI + Backend) | D4: digishop-vendor / digishop-storefront | E4: feature/v2-dashboard-analytics-theme | F4: Vendor
A5: V3 | B5: Iqra Ashraf | C5: Vendor Products, Inventory, AI Image & Copy Tools (UI + Backend) | D5: digishop-vendor | E5: feature/v3-catalog-inventory-ai | F5: Vendor
A6: V4 | B6: Tahleel Fatima/ Kiran Mukhtar | C6: Vendor Orders, Storefront Checkout, Marketing & Wallet/VCC (UI + Backend) | D6: digishop-vendor / digishop-storefront | E6: feature/v4-orders-checkout-marketing-wallet | F6: Vendor
A7: A1 | B7: Malaika Majeed | C7: Admin Shell, Vendor Management, Design System & Platform Analytics (UI + Backend) | D7: digishop-admin / digishop-shared | E7: feature/a1-admin-shell-design-vendor-mgmt | F7: Admin
A8: A2 | B8: Hiba Maroof | C8: Admin Escrow Ops, Finance, Refunds & Subscription Management (UI + Backend) | D8: digishop-admin | E8: feature/a2-escrow-finance-refunds | F8: Admin
A9: A3 | B9: Areeba Shakeel | C9: Admin Logistics, Courier Partners & Domain Reseller Operations (UI + Backend) | D9: digishop-admin | E9: feature/a3-logistics-couriers-domains | F9: Admin
A10: A4 | B10: Manahil Asif | C10: Admin Email Infra, Security, DevOps & Shared AI Core Services (UI + Backend) | D10: digishop-admin / digishop-shared | E10: feature/a4-email-security-ai-core | F10: Admin
A12: How the split works:
A13: • VENDOR SIDE (V1-V4) = the vendor panel + the auto-generated public storefront their customers browse and buy from.
A14: • ADMIN SIDE (A1-A4) = the internal panel used by the DigiShop AI team to manage all vendors, escrow, domains, couriers, email, security.
A15: • Every member owns a full vertical slice: they build the UI screens AND the backend/APIs/integrations for their slice. No pure-UI or pure-backend roles.
A16: • Cross-slice dependencies are called out in the Dependencies column of the Task Tracker.
A17: • A4 (Admin) also owns shared services (WhatsApp AI core, Meta Ads shared service, design system tokens) that V-side members consume.

Sheet Task Tracker
E1: DigiShop AI — Task Tracker (Phase 1: Web App Launch, 0 → 1,000 Vendors)
A2: Task ID | B2: Member | C2: Side | D2: Feature Area | E2: Task Title | F2: Type | G2: Detailed Description (What to build & how) | H2: Acceptance Criteria | I2: Priority | J2: Est. Days | K2: Dependencies | L2: Status
A3: T-V1-001 | B3: V1 | C3: Vendor | D3: Auth UI | E3: Vendor Signup Page — Full UI | F3: UI | G3: Build the vendor signup page in Next.js. Form fields: full name, business name, phone (with +92 prefix and validation), email, password with strength meter, category dropdown, terms & privacy checkbox. Include social signup buttons (Google, Facebook). Design must follow the 3D premium tokens from A1's design system. Loading, error, and success states all designed. Show OTP verification step immediately after phone submission. | H3: All form validations trigger inline errors; password meter shows weak/medium/strong; social buttons render; terms link opens modal; page is fully responsive on 1280px+ and mobile; matches design tokens. | I3: P0 | J3: 3 | K3: A1 design system (V1-DEPS-1) | L3: In Progress
A4: T-V1-002 | B4: V1 | C4: Vendor | D4: Auth UI | E4: Vendor Login Page + Forgot Password Flow — UI | F4: UI | G4: Build vendor login page with email-or-phone + password fields. Add 'Remember me' checkbox. 'Forgot password' link opens a modal where vendor enters email → receives reset link → clicks link → new password page. Design the three screens (login, forgot-modal, reset) with consistent styling. Support Google/Facebook social login buttons here too. | H4: Wrong credentials show inline error; social login redirects correctly; forgot-password flow works end-to-end; reset link expires visually after 1 hour. | I4: P0 | J4: 2 | K4: Auth backend (V1) | L4: In Progress
A5: T-V1-003 | B5: V1 | C5: Vendor | D5: Onboarding UI | E5: 4-Step Onboarding Wizard — Full UI Layer | F5: UI | G5: Build a full-screen 4-step wizard shown after signup: (1) Welcome + business info form (name, category, target region, expected products); (2) Product prompt input ('What do you sell?' with example prompts below); (3) Theme selection — display 4-6 AI-generated theme previews in a grid, vendor picks one; (4) Add first product + celebration. Include a progress bar (25/50/75/100%) at the top, back/next buttons with proper state preservation, and skip options where allowed. | H5: All 4 steps navigate correctly; progress bar updates; back preserves state; wizard remembers where user left off if they close/reopen. | I5: P0 | J5: 5 | K5: V2 theme engine backend, V3 add-product form | L5: In Progress
A6: T-V1-004 | B6: V1 | C6: Vendor | D6: Onboarding UI | E6: Onboarding Progress Persistence UI | F6: UI | G6: If a vendor abandons the wizard midway, when they log back in, show a 'Continue onboarding' banner on the dashboard that resumes them at the exact step they left. Also build a 'Complete your setup' checklist widget on the dashboard for post-onboarding items (add 3 more products, connect domain, add courier). | H6: Resume flow works from any step; checklist accurately reflects vendor progress; ticking off items updates instantly. | I6: P1 | J6: 2 | K6: Onboarding wizard, dashboard shell from V2 | L6: In Progress
A7: T-V1-005 | B7: V1 | C7: Vendor | D7: Profile UI | E7: Business Profile Settings Page — UI | F7: UI | G7: Full profile settings page split into tabs: Business Info (name, category, description, address, phone, business email, logo upload to Cloudinary), Notification Preferences (toggles for order alerts, low stock, new campaign, WhatsApp forwards, marketing tips), Team Members (list + invite by email with Admin/Editor/Viewer role), Security (change password, active sessions, logout everywhere). | H7: All 4 tabs functional; logo upload works and appears in storefront header; team invites send email; changing password logs out other sessions. | I7: P0 | J7: 4 | K7: Cloudinary integration (V3), Resend (A4) | L7: In Progress
A8: T-V1-006 | B8: V1 | C8: Vendor | D8: Subscription UI | E8: Subscription Plans Page — UI | F8: UI | G8: Show 3 plan cards side-by-side (Starter / Growth / Scale) with feature comparison, current plan highlighted with a badge, upgrade/downgrade CTAs. Include a FAQ accordion below and a 'contact sales' link for custom enterprise plans. Also show a billing history table below plans. | H8: Cards render correctly; features accurate; current plan clearly marked; CTA opens the payment/top-up flow; billing history loads. | I8: P0 | J8: 3 | K8: Subscription backend, A2 subscription mgmt | L8: In Progress
A9: T-V1-007 | B9: V1 | C9: Vendor | D9: Subscription UI | E9: PKR Wallet Top-Up Flow — UI | F9: UI | G9: Wallet top-up modal: vendor enters amount, selects gateway (JazzCash / EasyPaisa / Bank Transfer), clicks 'Top Up' → redirected to gateway → returns to success or failure page. Show a 'digital invoice' option too where they get a payment link. | H9: Redirect works; success updates wallet balance instantly; failure gives clear retry option; digital invoice link shareable. | I9: P0 | J9: 3 | K9: V4 payment gateway integration (shared) | L9: In Progress
A10: T-V1-008 | B10: V1 | C10: Vendor | D10: Auth Backend | E10: Supabase Auth Setup — Vendors Table + JWT Config | F10: Backend | G10: Configure Supabase Auth for email/password + phone OTP. Create the `vendors` table (id, name, business_name, phone, email, category, region, status, created_at, updated_at) with proper indexes. Set JWT expiry to 1 hour with refresh token rotation. Create Row Level Security (RLS) policies so a vendor can only read/update their own row. | H10: JWT issued on login; refresh works silently; RLS policies pass unit tests; vendor cannot query another vendor's row. | I10: P0 | J10: 3 | K10: Supabase project (A4) | L10: In Progress
A11: T-V1-009 | B11: V1 | C11: Vendor | D11: Auth Backend | E11: OAuth Integration (Google + Facebook) | F11: Backend | G11: Wire Google and Facebook OAuth via Supabase Auth. Handle callback URL, extract profile (email, name, avatar), auto-create vendor row on first login, link existing vendor if email matches. Handle edge cases: email already registered with password auth (offer to link), Facebook email missing (fallback to prompt). | H11: OAuth login end-to-end works; existing users not duplicated; missing-email fallback works; audit log entry created for every OAuth login. | I11: P0 | J11: 3 | K11: Supabase Auth base, Meta developer account | L11: In Progress
A12: T-V1-010 | B12: V1 | C12: Vendor | D12: Auth Backend | E12: Phone OTP Verification via WhatsApp Business API | F12: Backend | G12: Send a 6-digit OTP to vendor's phone via WhatsApp Business API (cheaper than SMS). Store OTP hashed in DB with 5-minute expiry. Verify endpoint compares hash. Block phone after 3 failed attempts for 15 minutes. | H12: OTP delivers within 10 seconds; wrong code blocks after 3 tries; expiry works; audit log for every attempt. | I12: P1 | J12: 3 | K12: WhatsApp Business API (A4 shared service) | L12: In Progress
A13: T-V1-011 | B13: V1 | C13: Vendor | D13: Auth Backend | E13: Password Reset Flow — Token & Email Trigger | F13: Backend | G13: Backend endpoint for password reset: /api/auth/reset-request generates a secure random token, stores it hashed with 1-hour expiry, fires an email via Resend to the vendor. /api/auth/reset-confirm verifies the token and updates the password hash. Old password immediately invalidated after reset. | H13: Full flow works; token single-use; expired tokens rejected with clear error; old sessions invalidated after reset. | I13: P0 | J13: 2 | K13: Resend email (A4) | L13: In Progress
A14: T-V1-012 | B14: V1 | C14: Vendor | D14: Onboarding Backend | E14: Onboarding State Machine + APIs | F14: Backend | G14: Backend to manage onboarding progress: /api/onboarding/step endpoint accepts step data and persists to the `vendor_onboarding` table. Fields: current_step, business_info_data, product_prompt, chosen_theme_id, first_product_id, completed_at. Emits event `onboarding_completed` when step 4 done, which triggers welcome email and Meta pixel install prompt. | H14: State survives crash/refresh; event fires exactly once; API idempotent per step. | I14: P0 | J14: 3 | K14: Vendors table, event bus | L14: In Progress
... A137: T-A4-017 | B137: A4 | C137: Admin | D137: Testing | E137: A4 Test Suite — Security + AI + Infra | F137: Testing | G137: Security: automated RLS tests (attempt cross-tenant every table). AI: mock conversation tests for WhatsApp AI. Infra: chaos tests (DB failover, LLM outage). | H137: RLS suite passes 100%; AI conversation quality manually reviewed and scored; chaos scenarios recovered. | I137: P0 | J137: 5 | K137: All A4 tasks | L137: In Review

Sheet Daily Standup Log
A1: Daily Standup Log — Fill in every working day
A2: Date | B2: Member | C2: Yesterday (Completed) | D2: Today (Working on) | E2: Blockers / Help needed | F2: Squad Lead comments
A3: 2026-08-11 (example) | B3: V1 | C3: Completed vendor signup form UI + validations (PR #12). | D3: Wiring up Supabase Auth backend + JWT config. | E3: Waiting on A4 for master env vars for OAuth secrets. | F3: Approved. A4 will DM env vars today.

Sheet Definition of Done
A1: Definition of Done — Every task ships only when all items ✓
A2: Category | B2: Checklist Item | C2: Applies to
A3: Code Quality | B3: Code follows ESLint + Prettier; zero warnings on push | C3: All
A4: Code Quality | B4: UI uses ONLY design tokens from A1's globals.css — no hardcoded colors, fonts, or spacing | C4: UI tasks
A5: Code Quality | B5: TypeScript strict mode passes; no `any` without justification comment | C5: All
A6: Code Quality | B6: Component/function naming follows repo conventions | C6: All
A7: Testing | B7: Unit tests written for new logic; existing tests pass on CI | C7: All
A8: Testing | B8: Playwright E2E covers happy path + at least one error case | C8: Full-Stack, Integration
A9: Testing | B9: Storybook story added for reusable components | C9: UI
A10: Testing | B10: Lighthouse Performance ≥85 and SEO ≥95 on affected storefront pages | C10: Storefront UI
A11: Security | B11: All API routes protected with JWT + RLS check; no unauthenticated data leak | C11: Backend
A12: Security | B12: Sensitive keys (courier, payment, VCC, OAuth tokens) encrypted at rest via A4's key vault | C12: Backend
A13: Security | B13: No secrets, PII, or card data in logs or console output (verified by log scanner) | C13: All
... A29: Monitoring | B29: Analytics events fired for user-facing actions | C29: UI
